balsnap/__init__.py
balsnap/balsnap.py
balsnap/utils.py
balsnap-0.3.1.dist-info/LICENSE
balsnap-0.3.1.dist-info/METADATA
balsnap-0.3.1.dist-info/WHEEL
balsnap-0.3.1.dist-info/top_level.txt
balsnap-0.3.1.dist-info/RECORD
