Metadata-Version: 2.1
Name: balsnap
Version: 0.3.1
Summary: A light-weight python library that help take balance snapshots of multiple tokens and accounts at once
Home-page: https://github.com/Soptq/balsnap
Author: Soptq
License: MIT
Project-URL: Bug Tracker, https://github.com/Soptq/balsnap/issues
Platform: UNKNOWN
Requires-Python: >=3.9
License-File: LICENSE
Requires-Dist: eth-brownie
Requires-Dist: prettytable
